__init__.py
es_ES/__init__.py
pt_PT/__init__.py
faker_utilities-0.1.1.dist-info/LICENSE
faker_utilities-0.1.1.dist-info/METADATA
faker_utilities-0.1.1.dist-info/WHEEL
faker_utilities-0.1.1.dist-info/top_level.txt
faker_utilities-0.1.1.dist-info/RECORD
